AUTHORS.rst
CONTRIBUTING.rst
HISTORY.rst
LICENSE
MANIFEST.in
README.rst
setup.cfg
setup.py
docs/Makefile
docs/authors.rst
docs/conf.py
docs/contributing.rst
docs/history.rst
docs/index.rst
docs/installation.rst
docs/make.bat
docs/readme.rst
docs/usage.rst
posh/__init__.py
posh/account.py
posh/cli.py
posh/posh.py
posh/product.py
posh/product_search.py
posh.egg-info/PKG-INFO
posh.egg-info/SOURCES.txt
posh.egg-info/dependency_links.txt
posh.egg-info/entry_points.txt
posh.egg-info/not-zip-safe
posh.egg-info/requires.txt
posh.egg-info/top_level.txt
tests/test_account.py
tests/test_db.py
tests/test_product.py
tests/test_search.py