Metadata-Version: 2.1
Name: posh
Version: 0.2
Summary: Aspiring Poshmark bot/scraper/etc.
Home-page: https://github.com/kcinnick/posh
Author: Nick Tucker
Author-email: nicktucker4@gmail.com
License: MIT license
Keywords: posh
Platform: UNKNOWN
Classifier: Development Status :: 2 - Pre-Alpha
Classifier: Intended Audience :: Developers
Classifier: License :: OSI Approved :: MIT License
Classifier: Natural Language :: English
Classifier: Programming Language :: Python :: 3.5
Classifier: Programming Language :: Python :: 3.6
Classifier: Programming Language :: Python :: 3.7
